{
    "posts": [
        
        {
            "title": "VSCode and Markdown Monster with Powershell",
            "url": "https://www.tiernanotoole.ie/2017/05/06/vscode-with-powershell.html",
            "date": "2017-05-06T13:00:00+00:00"
        },
        
        {
            "title": "Zerotier and Mini Followup",
            "url": "https://www.tiernanotoole.ie/2017/05/05/zerotier-minio-update.html",
            "date": "2017-05-05T16:00:00+00:00"
        },
        
        {
            "title": "Business Class Broadband... finally here....",
            "url": "https://www.tiernanotoole.ie/2017/03/09/business-class-broadband.html",
            "date": "2017-03-09T21:00:00+00:00"
        },
        
        {
            "title": "Distributed S3 data storage using Minio (and Zerotier)",
            "url": "https://www.tiernanotoole.ie/2017/01/19/distributed-s3-storage-minio-zerotier.html",
            "date": "2017-01-19T18:00:00+00:00"
        },
        
        {
            "title": "Docker Jekyll and Mr ngrok",
            "url": "https://www.tiernanotoole.ie/2016/11/15/docker-jekyll-and-mr-ngrock.html",
            "date": "2016-11-15T12:00:00+00:00"
        },
        
        {
            "title": "Building Jekyll sites with Docker on Windows",
            "url": "https://www.tiernanotoole.ie/2016/11/02/building-jekyll-sites-with-docker-on-windows.html",
            "date": "2016-11-02T08:00:00+00:00"
        },
        
        {
            "title": "Cloud Desktop becoming a reality",
            "url": "https://www.tiernanotoole.ie/2016/09/14/cloud-desktop-becoming-reality.html",
            "date": "2016-09-14T16:00:00+00:00"
        },
        
        {
            "title": "double speed Internet Part 9 - Going Back",
            "url": "https://www.tiernanotoole.ie/2016/07/20/double-speed-internet-part-9-going-back.html",
            "date": "2016-07-20T12:00:00+00:00"
        },
        
        {
            "title": "Meraki and Ubiquiti networks gear Update",
            "url": "https://www.tiernanotoole.ie/2016/06/20/meraki-gear-update.html",
            "date": "2016-06-20T08:00:00+00:00"
        },
        
        {
            "title": "double speed Internet Part 8 - Routing Around",
            "url": "https://www.tiernanotoole.ie/2016/06/08/double-speed-internet-part-8-routing-around.html",
            "date": "2016-06-08T08:00:00+00:00"
        },
        
        {
            "title": "double speed Internet Part 7 - ECMP (kind of)",
            "url": "https://www.tiernanotoole.ie/2016/05/31/double-speed-internet-part-7-ecmp-kind-of.html",
            "date": "2016-05-31T06:00:00+00:00"
        },
        
        {
            "title": "double speed Internet Part 6 - Hetzner Edition",
            "url": "https://www.tiernanotoole.ie/2016/05/17/double-speed-internet-part-6-hetzner-edition.html",
            "date": "2016-05-17T13:00:00+00:00"
        },
        
        {
            "title": "Useful Web and Desktop Apps 2016 edition",
            "url": "https://www.tiernanotoole.ie/2016/04/23/useful-web-and-desktop-apps-2016-edition.html",
            "date": "2016-04-23T22:50:00+00:00"
        },
        
        {
            "title": "(Mad) Max Speed - The Road Warrior (Internet connection) (double speed internet Part 5)",
            "url": "https://www.tiernanotoole.ie/2016/04/21/2-cable-modems-double-speed-part-5.html",
            "date": "2016-04-21T21:33:00+00:00"
        },
        
        {
            "title": "2 Cable Modems = Double Speed? Part 4",
            "url": "https://www.tiernanotoole.ie/2016/04/14/2-cable-modems-double-speed-part-4.html",
            "date": "2016-04-14T08:55:00+00:00"
        },
        
        {
            "title": "Installing Jekyll on Bash On Ubuntu on Windows",
            "url": "https://www.tiernanotoole.ie/2016/04/11/installing-jekyll-on-bash-on-ubuntu-on-windows.html",
            "date": "2016-04-11T10:09:00+00:00"
        },
        
        {
            "title": "2 Cable modems = Double speed? Part 3",
            "url": "https://www.tiernanotoole.ie/2016/04/02/2-cable-modems-double-speed-part-3.html",
            "date": "2016-04-02T17:48:00+00:00"
        },
        
        {
            "title": "Bash on Ubuntu on Windows",
            "url": "https://www.tiernanotoole.ie/2016/03/31/bash-on-ubuntu-on-windows.html",
            "date": "2016-03-31T07:00:00+00:00"
        },
        
        {
            "title": "MPTCP, SSH, Squid, OpenVPN (and 2 Cable modems) = Double Speed? Not quite... Part 2",
            "url": "https://www.tiernanotoole.ie/2016/03/30/mptcp-ssh-squid-openvpn-double-speed-part-2.html",
            "date": "2016-03-30T20:00:00+00:00"
        },
        
        {
            "title": "Continuous Integration and Blogging",
            "url": "https://www.tiernanotoole.ie/2016/03/24/Continuous-Integration-And-Blogging.html",
            "date": "2016-03-24T08:00:00+00:00"
        },
        
        {
            "title": "2 Cable modems = Double Internet Speed? Well... not really... Part 1",
            "url": "https://www.tiernanotoole.ie/2016/03/22/2-Cable-Modems-Double-Internet-Speed-part1.html",
            "date": "2016-03-22T18:00:00+00:00"
        },
        
        {
            "title": "Announcing B2 Uploader and Hubic Testing 2.0",
            "url": "https://www.tiernanotoole.ie/2016/01/15/Announcing-B2Uploader-HubicTesting20.html",
            "date": "2016-01-15T23:55:00+00:00"
        },
        
        {
            "title": "Edge Router, Sophos UTM, DMZ and LAN Networks",
            "url": "https://www.tiernanotoole.ie/2015/09/30/EdgeRouter-SophosUTM-DMZ-LAN-Firwwalls.html",
            "date": "2015-09-30T20:00:00+00:00"
        },
        
        {
            "title": "Network and HomeLab V.Next (Part 4)",
            "url": "https://www.tiernanotoole.ie/2015/09/16/Network-and-HomeLab-vnext-part-4.html",
            "date": "2015-09-16T14:15:00+00:00"
        },
        
        {
            "title": "Windows Server 2012 R2 returning to The GodBoxV2",
            "url": "https://www.tiernanotoole.ie/2015/08/23/WindwsServer2012r2-Returing-To-The-GodBoxV2.html",
            "date": "2015-08-23T20:00:00+00:00"
        },
        
        {
            "title": "ZFS Home storage pool",
            "url": "https://www.tiernanotoole.ie/2015/08/10/ZFS-Home-dir.html",
            "date": "2015-08-10T11:40:00+00:00"
        },
        
        {
            "title": "Ubiquiti EdgeRouter PoE in the lab",
            "url": "https://www.tiernanotoole.ie/2015/08/05/Ubiquiti-EdgeRouter-POE-In-the-lab.html",
            "date": "2015-08-05T21:00:00+00:00"
        },
        
        {
            "title": "Network and HomeLab V.Next (Part 3)",
            "url": "https://www.tiernanotoole.ie/2015/07/16/Network-and-HomeLab-vnext-part-3.html",
            "date": "2015-07-16T13:15:00+00:00"
        },
        
        {
            "title": "Network and HomeLab V.Next (Part 2)",
            "url": "https://www.tiernanotoole.ie/2015/06/23/Network-and-HomeLab-vnext-part2.html",
            "date": "2015-06-23T10:30:00+00:00"
        },
        
        {
            "title": "Network and Homelab V.Next (Part 1)",
            "url": "https://www.tiernanotoole.ie/2015/06/14/Network-and-homelab-vnext-part-1.html",
            "date": "2015-06-14T16:05:00+00:00"
        },
        
        {
            "title": "PFSense with Multiple Public IPs",
            "url": "https://www.tiernanotoole.ie/2015/05/30/PFSense-with-multiple-public-ips.html",
            "date": "2015-05-30T18:50:00+00:00"
        },
        
        {
            "title": "Quick tip for internet facing ESXi servers",
            "url": "https://www.tiernanotoole.ie/2015/05/20/quick-tip-for-internet-facing-esxi.html",
            "date": "2015-05-20T08:12:00+00:00"
        },
        
        {
            "title": "VLANs, Wifi and Mikrotik",
            "url": "https://www.tiernanotoole.ie/2015/05/10/vlans-wifi-and-mikrotik.html",
            "date": "2015-05-10T18:40:00+00:00"
        },
        
        {
            "title": "Using git and Route53 together",
            "url": "https://www.tiernanotoole.ie/2015/05/07/using-git-and-route53.html",
            "date": "2015-05-07T20:00:00+00:00"
        },
        
        {
            "title": "Git Push DNS",
            "url": "https://www.tiernanotoole.ie/2015/05/07/git-push-dns.html",
            "date": "2015-05-07T15:30:00+00:00"
        },
        
        {
            "title": "Bulk compressing images for the Web",
            "url": "https://www.tiernanotoole.ie/2015/04/29/bulk-compressing-images-for-the-web.html",
            "date": "2015-04-29T17:00:00+00:00"
        },
        
        {
            "title": "All blogs moved to Jekyll",
            "url": "https://www.tiernanotoole.ie/2015/04/28/all-blogs-moved-to-jekyll.html",
            "date": "2015-04-28T12:49:53+00:00"
        },
        
        {
            "title": "Hubic and Duplicity",
            "url": "https://www.tiernanotoole.ie/2015/04/01/Duplicity_Hubic.html",
            "date": "2015-04-01T07:00:00+00:00"
        },
        
        {
            "title": "Hubic, OpenStack Swift and Curl",
            "url": "https://www.tiernanotoole.ie/2015/03/31/HubiC_SWIFT_CURL.html",
            "date": "2015-03-31T22:40:00+00:00"
        },
        
        {
            "title": "Daily Carry, March 2015 Edition",
            "url": "https://www.tiernanotoole.ie/2015/03/26/Daily_Carry.html",
            "date": "2015-03-26T21:41:00+00:00"
        },
        
        {
            "title": "Mobile Phone as a Service",
            "url": "https://www.tiernanotoole.ie/2015/02/15/mobile_phone_as_a_service.html",
            "date": "2015-02-15T21:47:00+00:00"
        },
        
        {
            "title": "CDN Hosted Blog",
            "url": "https://www.tiernanotoole.ie/2014/01/23/CDNHostedBlog.html",
            "date": "2014-01-23T00:00:00+00:00"
        },
        
        {
            "title": "Raspberry Pi as an Asterisk Box",
            "url": "https://www.tiernanotoole.ie/2013/05/29/RaspberryPi_Astrisk_Box.html",
            "date": "2013-05-29T08:16:00+00:00"
        },
        
        {
            "title": "College Bag Contents",
            "url": "https://www.tiernanotoole.ie/2013/01/27/college_bag_contents.html",
            "date": "2013-01-27T22:28:58+00:00"
        },
        
        {
            "title": "Raspberry Pi as a Mobile WiFi HotSpot (part 1)",
            "url": "https://www.tiernanotoole.ie/2013/01/18/raspberry_pi_as_a_mobile_wifi_hotspot_-_part_1.html",
            "date": "2013-01-18T07:57:16+00:00"
        },
        
        {
            "title": "Moving sites to NearlyFreeSpeech",
            "url": "https://www.tiernanotoole.ie/2013/01/15/moving_sites_to_nearlyfreespeech.html",
            "date": "2013-01-15T19:23:02+00:00"
        },
        
        {
            "title": "Send Emails as a Distribution Group in Office365",
            "url": "https://www.tiernanotoole.ie/2012/12/20/send_emails_as_a_distribution_group_in_office365.html",
            "date": "2012-12-20T13:13:21+00:00"
        },
        
        {
            "title": "IPv6 Firewall rules for MikroTik RouterOS",
            "url": "https://www.tiernanotoole.ie/2012/12/20/ipv6_firewall_rules_for_mikrotik_routeros.html",
            "date": "2012-12-20T11:09:06+00:00"
        },
        
        {
            "title": "IPv6 + MikroTik + Linux + Windows",
            "url": "https://www.tiernanotoole.ie/2012/12/19/ipv6_+_mikrotik_+_linux_+_windows.html",
            "date": "2012-12-19T16:24:07+00:00"
        },
        
        {
            "title": "Compressing and UnCompressing Protobuf items in C#",
            "url": "https://www.tiernanotoole.ie/2012/12/12/compressing_and_uncompressing_protobuf_items_in_c.html",
            "date": "2012-12-12T11:29:32+00:00"
        },
        
        {
            "title": "GIT tips and tricks",
            "url": "https://www.tiernanotoole.ie/2012/12/05/git_tips_and_tricks.html",
            "date": "2012-12-05T15:48:44+00:00"
        },
        
        {
            "title": "Symform - P2P Backup",
            "url": "https://www.tiernanotoole.ie/2012/11/30/symform_-_p2p_backup.html",
            "date": "2012-11-30T09:13:27+00:00"
        },
        
        {
            "title": "enabling VNC from SSH on OSX",
            "url": "https://www.tiernanotoole.ie/2012/11/29/enabling_vnc_from_ssh_on_osx.html",
            "date": "2012-11-29T16:16:49+00:00"
        },
        
        {
            "title": "moving your TMG SQL server Logs DB and other TMG tips",
            "url": "https://www.tiernanotoole.ie/2012/11/22/moving_your_tmg_sql_server_and_other_tmg_tips.html",
            "date": "2012-11-22T08:27:55+00:00"
        },
        
        {
            "title": "RouterOS Dynamic IP Updates",
            "url": "https://www.tiernanotoole.ie/2012/11/19/routeros_dynamic_ip_updates.html",
            "date": "2012-11-19T10:19:26+00:00"
        },
        
        {
            "title": "Custom MSDeploy OverWrite Rules",
            "url": "https://www.tiernanotoole.ie/2012/10/31/custom_msdeploy_overwrite_rules.html",
            "date": "2012-10-31T09:45:54+00:00"
        },
        
        {
            "title": "WANProxy and Squid with Upstream Servers",
            "url": "https://www.tiernanotoole.ie/2012/10/26/wanproxy_and_squid_with_upstream_servers.html",
            "date": "2012-10-26T13:14:00+00:00"
        },
        
        {
            "title": "Building WANProxy on Ubuntu 12.04",
            "url": "https://www.tiernanotoole.ie/2012/10/24/building_wanproxy_on_ubuntu_12.04.html",
            "date": "2012-10-24T14:28:07+00:00"
        },
        
        {
            "title": "Boot Raspberry Pi with SSH Enabled, Enable Wifi on Boot, and more",
            "url": "https://www.tiernanotoole.ie/2012/10/18/boot_raspberry_pi_with_ssh_enabled.html",
            "date": "2012-10-18T16:45:01+00:00"
        },
        
        {
            "title": "GPS and Raspberry Pi",
            "url": "https://www.tiernanotoole.ie/2012/10/15/gps_and_raspberry_pi.html",
            "date": "2012-10-15T16:20:17+00:00"
        },
        
        {
            "title": "Raspberry Pi now with 512MB RAM, other random links...",
            "url": "https://www.tiernanotoole.ie/2012/10/15/raspberry_pi_now_with_512mb_ram.html",
            "date": "2012-10-15T12:37:20+00:00"
        },
        
        {
            "title": "more raspberry pi and camera antics",
            "url": "https://www.tiernanotoole.ie/2012/10/12/more_raspberry_pi_and_camera_antics.html",
            "date": "2012-10-12T15:13:53+00:00"
        },
        
        {
            "title": "RouterOS Using Host names in Firewall Rules",
            "url": "https://www.tiernanotoole.ie/2012/10/12/routeros_using_host_names_in_firewall_rules.html",
            "date": "2012-10-12T07:43:17+00:00"
        },
        
        {
            "title": "RouterOS Blocking Machine access to all but one IP",
            "url": "https://www.tiernanotoole.ie/2012/10/11/routeros_blocking_machine_access.html",
            "date": "2012-10-11T13:09:20+00:00"
        },
        
        {
            "title": "ZFS iSCSI NFS SFTP Hyper-V and more",
            "url": "https://www.tiernanotoole.ie/2012/10/05/zfs_iscsi_nfs_sftp_hyper-v_and_more.html",
            "date": "2012-10-05T09:38:13+00:00"
        },
        
        {
            "title": "More Jekyll Stuff",
            "url": "https://www.tiernanotoole.ie/2012/10/04/more_jekyll_stuff.html",
            "date": "2012-10-04T20:57:52+00:00"
        },
        
        {
            "title": "Handbrake Cluster",
            "url": "https://www.tiernanotoole.ie/2012/10/03/Handbrake-Cluster.html",
            "date": "2012-10-03T00:00:00+00:00"
        },
        
        {
            "title": "Enabling True Bridging modem on a Cisco ECP3925 Cable Modem (UPC Ireland)",
            "url": "https://www.tiernanotoole.ie/2012/10/02/Enabling-true-briding-mode-on-Cisco-EPC3925.html",
            "date": "2012-10-02T00:00:00+00:00"
        },
        
        {
            "title": "PowerShell + HandBrake + AppleTV + iTunes = Automatic TV... Ish...",
            "url": "https://www.tiernanotoole.ie/2012/09/28/Powershell-HandBrake-AppleTV-iTunes.html",
            "date": "2012-09-28T00:00:00+00:00"
        },
        
        {
            "title": "More VoIP Stuff",
            "url": "https://www.tiernanotoole.ie/2012/09/27/More-VoIP-Stuff.html",
            "date": "2012-09-27T00:00:00+00:00"
        },
        
        {
            "title": "Building a Cross Compiler for your Raspberry Pi",
            "url": "https://www.tiernanotoole.ie/2012/09/25/Raspberry-Pi-Cross-Compiling.html",
            "date": "2012-09-25T00:00:00+00:00"
        },
        
        {
            "title": "MicroTik RouterOS VPN Setup",
            "url": "https://www.tiernanotoole.ie/2012/09/24/MicroTik-RouterOS-VPN-Setup.html",
            "date": "2012-09-24T00:00:00+00:00"
        },
        
        {
            "title": "SSH Tunneling made simple",
            "url": "https://www.tiernanotoole.ie/2012/09/17/SSH-Tunneling-Made-Simple.html",
            "date": "2012-09-17T00:00:00+00:00"
        },
        
        {
            "title": "VOIP Stuff",
            "url": "https://www.tiernanotoole.ie/2012/09/11/VOIP-Stuff.html",
            "date": "2012-09-11T00:00:00+00:00"
        },
        
        {
            "title": "Raspberry Pi Stuff",
            "url": "https://www.tiernanotoole.ie/2012/09/06/Rasberry-Stuff.html",
            "date": "2012-09-06T00:00:00+00:00"
        },
        
        {
            "title": "Build your own Private GIT server",
            "url": "https://www.tiernanotoole.ie/2012/09/03/Build-Your-Own-Private-Git-Server.html",
            "date": "2012-09-03T10:28:11+00:00"
        },
        
        {
            "title": "Crashplan Backups",
            "url": "https://www.tiernanotoole.ie/2012/08/30/CrashPlan-Backups.html",
            "date": "2012-08-30T11:32:32+00:00"
        },
        
        {
            "title": "Understanding Storage Spaces in Windows 8 and Windows Server 2012",
            "url": "https://www.tiernanotoole.ie/2012/08/30/Understanding-Windows8-Storage-Spaces.html",
            "date": "2012-08-30T09:04:14+00:00"
        },
        
        {
            "title": "Sublime Text 2 with Powershell",
            "url": "https://www.tiernanotoole.ie/2012/08/30/SublimeText-With-Powershell.html",
            "date": "2012-08-30T09:00:13+00:00"
        },
        
        {
            "title": "AutoScaling with Amazon",
            "url": "https://www.tiernanotoole.ie/2012/08/30/AutoScalling-With-Amazon.html",
            "date": "2012-08-30T00:00:00+00:00"
        },
        
        {
            "title": "My new Git Powered Site",
            "url": "https://www.tiernanotoole.ie/2012/08/29/NewSite.html",
            "date": "2012-08-29T12:54:40+00:00"
        }
        
    ]
}
